README.md
flask_serverinfo.py
setup.py
Flask_ServerInfo.egg-info/PKG-INFO
Flask_ServerInfo.egg-info/SOURCES.txt
Flask_ServerInfo.egg-info/dependency_links.txt
Flask_ServerInfo.egg-info/namespace_packages.txt
Flask_ServerInfo.egg-info/requires.txt
Flask_ServerInfo.egg-info/top_level.txt
Flask_ServerInfo.egg-info/zip-safe